<?xml version="1.0" encoding="UTF-8" standalone="yes"?>
<addons>
<addon id="repository.boxopi" name="[COLOR lime]repositorioBOXOPOI[/COLOR] Repo" version="1.0.1" provider-name="Gabito">
    <extension point="xbmc.addon.repository" name="boxopi">
        <info>https://raw.githubusercontent.com/Gabitokodi/boxopi_repo/master/Repositorio/addons.xml</info>
        <checksum>https://raw.githubusercontent.com/Gabitokodi/boxopi_repo/master/Repositorio/addons.xml.md5</checksum>
        <datadir zip="true">https://raw.githubusercontent.com/Gabitokodi/master/Repositorio/</datadir>
    </extension>
    <extension point="xbmc.addon.metadata">
        <summary>Repositorio de BOXOPI</summary>
        <description></description>
        <disclaimer></disclaimer>
        <platform>all</platform>
    </extension>
</addon>

<addon id="repository.alfa-addon" name="[COLOR red]Alfa-Addon[/COLOR] Repo" version="1.0.4" provider-name="Alfa Addon">
    <requires>
        <import addon="xbmc.addon" version="12.0.0"/>
    </requires>
    <extension point="xbmc.addon.repository" name="Alfa-Addon Repo">
        <info>https://github.com/alfa-addon/alfa-repo/raw/master/addons.xml</info>
        <checksum>https://github.com/alfa-addon/alfa-repo/raw/master/addons.xml.md5</checksum>
        <datadir zip="true">https://github.com/alfa-addon/alfa-repo/raw/master</datadir>
    </extension>
    <extension point="xbmc.addon.metadata">
        <summary>Repositorio para Alfa-Addon</summary>
        <description></description>
        <disclaimer>The owners and submitters to this repository do not host or distribute any of the content displayed by these addons nor do they have any affiliation with the content providers.</disclaimer>
        <platform>all</platform>
    </extension>
</addon>

<addon id="plugin.video.elementum" name="Elementum" version="0.0.66" provider-name="elgatito">
    <requires>
        <import addon="xbmc.addon" version="16.0.0" />
        <import addon="xbmc.python" version="2.24.0" />
        <import addon="repository.elementum" optional="true" />
    </requires>
    <extension point="xbmc.python.pluginsource" library="navigation.py">
        <provides>video</provides>
    </extension>
    <extension point="xbmc.service" library="service.py" start="startup" />
    <extension point="xbmc.python.module" library="resources/site-packages" />
    <extension point="xbmc.subtitle.module" library="navigation.py" />
    <extension point="xbmc.addon.metadata">
        <summary lang="en">Elementum: Media streaming</summary>
        <summary lang="hr">Elementum: Medijsko strujanje</summary>
         <summary lang="es">Elementum: Transmisión de medios</summary>
        <description lang="en">Elementum is a torrent finding and streaming engine. It doesn't go on torrent websites for legal reasons. However, it calls specially crafted add-ons (called providers) that are installed separately.[CR]This project is a fork of the well known, but no longer maintained Pulsar/Quasar projects from steeve and scakemyer.</description>
        <description lang="hr">Elementum je pogon pretraživanja i strujanja. Ne posjećuje torrent web stranice iz pravnih razloga. Ipak, koristi posebno napravljene dodatke (nazvane pružatelji usluge) koji su instalirani odvojeno.[CR]Ovaj projekt je ogranak dobro poznatih, ali više ne održavanih Pulsar/Quasar projekata od autora steevea i scakemyera.</description>
        <description lang="es">Elementum es un motor de búsqueda y transmisión de torrents. No navega por sitios web de torrents por razones legales. Sin embargo, llama a complementos especialmente diseñados para ello (denominados providers o proveedores) que se instalan por separado.[CR]Este proyecto es un fork de los bien conocidos, pero ya sin soporte proyectos Pulsar/Quasar de steeve y scakemyer.[CR]</description>
        <disclaimer lang="en">The author does not own or host any content found within this Addon. The author is not connected to or in any other way affiliated with Kodi, Team Kodi, or the XBMC Foundation.</disclaimer>
        <disclaimer lang="hr">Autor ovog dodatka ne posjeduje i ne distribuira bilo kakav sadržaj koji je pronađen. Autor nije povezan sa ili na bilo koji drugi način bilo sa Kodijem, Team Kodijem ili XBMC fundacijom.</disclaimer>
        <disclaimer lang="es">El autor no posee ni aloja ningún contenido que se encuentre a través de este complemento. El autor no está unido ni relacionado de ninguna manera con Kodi, Team Kodi, o XBMC Foundation.</disclaimer>
        <language>en el es de fi fr he hr it nl pt ro sk</language>
        <platform>all</platform>
        <website>http://elementum.surge.sh/</website>
        <source>https://github.com/elgatito/plugin.video.elementum</source>
        <forum></forum>
        <license>Non commercial. See https://github.com/elgatito/plugin.video.elementum/blob/master/LICENSE</license>
        <assets>
            <icon>icon.png</icon>
            <fanart>fanart.png</fanart>
            <screenshot>resources/screenshots/home.png</screenshot>
            <screenshot>resources/screenshots/movies.png</screenshot>
            <screenshot>resources/screenshots/webui.png</screenshot>
        </assets>
    </extension>
</addon>

<addon id="plugin.video.cristalazul"
       name="[COLOR aqua]CRISTAL AZUL[/COLOR]"
       version="0.0.4"
       provider-name="PICAPAU, LOURDES, SUPERTOPO">
  <requires>
    <import addon="xbmc.python" version="2.1.0"/>
    <import addon="script.module.beautifulsoup" version="3.2.1"/>
    <import addon="script.module.simple.downloader" version="0.9.4"/>
    <import addon="script.module.beautifulsoup4" />
    <import addon="script.module.requests" />
    <import addon="script.module.httplib2" />
    <import addon="script.module.liveresolver" version="0.1.24" optional="true"/>
    <import addon="script.module.youtube.dl" optional="true"/>
    <import addon="plugin.video.youtube" />
    <import addon="script.module.urlresolver" />
	<import addon="script.module.simplejson" />
    <import addon="script.module.livestreamer" optional="true"/>
    <import addon="script.module.pyamf" optional="true"/>
  </requires>
  <extension point="xbmc.python.pluginsource" library="default.py">
    <provides>video</provides>
  </extension>

   <extension point="xbmc.addon.repository" name="Mi repositorio">
        <info>https://raw.githubusercontent.com/picapaujulen/repositorio/master/Repositorio/addons.xml</info>
        <checksum>https://raw.githubusercontent.com/picapaujulen/repositorio/master/Repositorio/addons.xml.md5</checksum>
        <datadir zip="true">https://raw.githubusercontent.com/picapaujulen/repositorio/master/Repositorio/</datadir>
    </extension>

  <extension point="xbmc.addon.metadata">
    <summary>creado por picapau, lourdes, supertopo y luisma</summary>
    <description>ESTE ADDON NO CONTIENE ENLACES PROPIOS,SON RECOPILACIONES DE LA RED, SOLO SE FACILITA EL ACESSO A ESAS WEBS, ESTAS WEBS SON LAS RESPONSABLES DE LOS CONTENIDOS
	</description>
    <platform>all</platform>
	  <assets>
		<icon>icon.gif</icon>
	  </assets>
  </extension>
</addon>
</addons>
